LICENSE
MANIFEST.in
README.md
setup.py
mdx_bleach/__init__.py
mdx_bleach/exceptions.py
mdx_bleach/extension.py
mdx_bleach/postprocessors.py
mdx_bleach/version.py
mdx_bleach/whitelist.py
mdx_bleach.egg-info/PKG-INFO
mdx_bleach.egg-info/SOURCES.txt
mdx_bleach.egg-info/dependency_links.txt
mdx_bleach.egg-info/requires.txt
mdx_bleach.egg-info/top_level.txt