Metadata-Version: 1.1
Name: mdx-bleach
Version: 0.1.0
Summary: Python Markdown extension to sanitize the output of untrustedMarkdown documents.
Home-page: https://github.com/Wenzil/mdx_bleach
Author: Sami Turcotte
Author-email: samiturcotte@gmail.com
License: MIT License
Download-URL: https://github.com/Wenzil/mdx_bleach/tarball/0.1.0
Keywords: mdx,bleach,markdown,extension,sanitize,html
Platform: UNKNOWN
Classifier: Development Status :: 4 - Beta
Classifier: Intended Audience :: Education
Classifier: License :: OSI Approved :: MIT License
Classifier: Natural Language :: English
Classifier: Operating System :: OS Independent
Classifier: Programming Language :: Python
Classifier: Programming Language :: Python :: 3
Classifier: Topic :: Software Development :: Libraries :: Python Modules
Classifier: Topic :: Text Processing :: Filters
Classifier: Topic :: Text Processing :: Markup :: HTML
